Metadata-Version: 2.1
Name: ProgressScript
Version: 1.0
Summary: Solid Progress Bar Script For Python 
Home-page: UNKNOWN
Author: IonE
Author-email: ivanaperginsky@gmail.com
License: UNKNOWN
Platform: UNKNOWN
Classifier: Programming Language :: Python :: 3
Classifier: License :: OSI Approved :: MIT License
Classifier: Operating System :: OS Independent
Requires-Python: >=3.6
